pyGenicCT/CTScores.py
pyGenicCT/__init__.py
pyGenicCT/plink_clump.py
pyGenicCT-0.2.0.dist-info/LICENSE
pyGenicCT-0.2.0.dist-info/METADATA
pyGenicCT-0.2.0.dist-info/WHEEL
pyGenicCT-0.2.0.dist-info/top_level.txt
pyGenicCT-0.2.0.dist-info/RECORD
