Metadata-Version: 2.1
Name: pyGenicCT
Version: 0.2.0
Summary: Clumping via plink and then p value thresh-holding through python
Home-page: UNKNOWN
Author: Samuel Baker
Author-email: samuelbaker.researcher@gmail.com
Maintainer: Samuel Baker
Maintainer-email: samuelbaker.researcher@gmail.com
License: MIT
Download-URL: https://github.com/sbaker-dev/pyGenicCT
Platform: UNKNOWN
Classifier: Programming Language :: Python :: 3.7
Classifier: License :: OSI Approved :: MIT License
Requires-Python: >=3.7
Requires-Dist: miscSupports
Requires-Dist: pandas
Requires-Dist: pysnptools
Requires-Dist: csvObject
Requires-Dist: numpy
